odoo/addons/pos_hide_empty_category/README.rst
odoo/addons/pos_hide_empty_category/__init__.py
odoo/addons/pos_hide_empty_category/__manifest__.py
odoo/addons/pos_hide_empty_category/demo/pos_category.xml
odoo/addons/pos_hide_empty_category/i18n/fr.po
odoo/addons/pos_hide_empty_category/i18n/pos_hide_empty_category.pot
odoo/addons/pos_hide_empty_category/readme/CONTRIBUTORS.rst
odoo/addons/pos_hide_empty_category/readme/DESCRIPTION.rst
odoo/addons/pos_hide_empty_category/static/description/icon.png
odoo/addons/pos_hide_empty_category/static/description/index.html
odoo/addons/pos_hide_empty_category/static/description/pos_category_tree_view.png
odoo/addons/pos_hide_empty_category/static/description/pos_front_ui.png
odoo/addons/pos_hide_empty_category/static/src/js/db.js
odoo/addons/pos_hide_empty_category/views/assets.xml
odoo12_addon_pos_hide_empty_category-12.0.1.0.2.dist-info/METADATA
odoo12_addon_pos_hide_empty_category-12.0.1.0.2.dist-info/WHEEL
odoo12_addon_pos_hide_empty_category-12.0.1.0.2.dist-info/top_level.txt
odoo12_addon_pos_hide_empty_category-12.0.1.0.2.dist-info/RECORD
